rtl/wptr_full.v
module wptr_full #(parameter ADDRESS_SIZE = 8)(
    output reg w_full,                   
    output [ADDRESS_SIZE-1:0] w_addr,       
    output reg [ADDRESS_SIZE :0] w_ptr,    
    input [ADDRESS_SIZE :0] w_q2_rptr,     
    input w_inc, w_clk, w_rst_n            
    );

    reg [ADDRESS_SIZE:0] w_bin;                     
    wire [ADDRESS_SIZE:0] w_gray_next, w_bin_next;   
    wire w_full_val;                             


    always @(posedge w_clk or negedge w_rst_n) begin
        if (!w_rst_n)         
            {w_bin, w_ptr} <= 0;
        else 
            {w_bin, w_ptr} <= {w_bin_next, w_gray_next}; 
    end

    assign w_addr = w_bin[ADDRESS_SIZE-1:0];             
    assign w_bin_next = w_bin + (w_inc & ~w_full);       
    assign w_gray_next = (w_bin_next>>1) ^ w_bin_next;    

    // Check if the FIFO is full
    //------------------------------------------------------------------
    // Simplified version of the three necessary full-tests:
    // assign w_full_val=((w_g_next[ADDRESS_SIZE] !=w_q2_rptr[ADDRESS_SIZE] ) &
    // (w_g_next[ADDRESS_SIZE-1] !=w_q2_rptr[ADDRESS_SIZE-1]) &
    // (w_g_next[ADDRESS_SIZE-2:0]==w_q2_rptr[ADDRESS_SIZE-2:0]));
    //------------------------------------------------------------------
    assign w_full_val = (w_gray_next=={~w_q2_rptr[ADDRESS_SIZE:ADDRESS_SIZE-1], w_q2_rptr[ADDRESS_SIZE-2:0]});

    always @(posedge w_clk or negedge w_rst_n) begin
        if (!w_rst_n)          
            w_full <= 1'b0;
        else 
            w_full <= w_full_val; 
    end
endmodule

Asynchronous Fifo/rtl/rptr_empty.v
module rptr_empty #(parameter ADDRESS_SIZE = 8)(
    output reg r_empty,                  
    output [ADDRESS_SIZE-1:0] r_addr,     
    output reg [ADDRESS_SIZE :0] r_ptr,  //read pointer(gray register)  
    input [ADDRESS_SIZE :0] r_q2_wptr,      
    input r_inc, r_clk, r_rst_n );

    reg [ADDRESS_SIZE:0] r_bin;                     // Binary register
    wire [ADDRESS_SIZE:0] r_gray_next, r_bin_next;   
    wire r_empty_val;                         

    // gray code pointer
    always @(posedge r_clk or negedge r_rst_n) begin
        if (!r_rst_n)               
            {r_bin, r_ptr} <= 1'b0;
        else 
            {r_bin, r_ptr} <= {r_bin_next, r_gray_next};  
    end

    assign r_addr = r_bin[ADDRESS_SIZE-1:0];                 
    assign r_bin_next = r_bin + (r_inc & ~r_empty);         
    assign r_gray_next = (r_bin_next>>1) ^ r_bin_next;     

    
    assign r_empty_val = (r_gray_next == r_q2_wptr);       

    always @(posedge r_clk or negedge r_rst_n) begin
        if (!r_rst_n)                
            r_empty <= 1'b1;
        else 
            r_empty <= r_empty_val;  
    end
endmodule

rtl/FIFO_memory.v
module FIFO_memory #(parameter DATA_SIZE = 16,
    parameter ADDRESS_SIZE = 8)(
    output [DATA_SIZE-1:0] r_data,       
    input [DATA_SIZE-1:0] w_data,       
    input [ADDRESS_SIZE-1:0] w_addr, r_addr,  
    input w_clk_en, w_full, w_clk          
    );

    localparam DEPTH = 1<<ADDRESS_SIZE;     
    reg [DATA_SIZE-1:0] mem [0:DEPTH-1];

    assign r_data = mem[r_addr];          

    always @(posedge w_clk)
        if (w_clk_en & ~w_full) mem[w_addr] <= w_data; 

endmodule

rtl/ff_synchronization.v
module ff_synchronization #(parameter ADDRESS_SIZE = 8)( 
    output reg [ADDRESS_SIZE:0] q2,   // synchronized input
    input [ADDRESS_SIZE:0] data_in,       // Data input
    input clk, rst_n);

    reg [ADDRESS_SIZE:0] q1; 

    always @(posedge clk or negedge rst_n) begin
        if (!rst_n) 
            {q2, q1} <= 0;         
        else 
            {q2, q1} <= {q1, data_in}; 
    end 

endmodule

Asynchronous Fifo/rtl/FIFO.V
module FIFO #(parameter DATA_SIZE = 16,
    parameter ADDRESS_SIZE = 8)(
    output [DATA_SIZE-1:0] r_data,       
    output w_full,                   
    output r_empty,                  
    input [DATA_SIZE-1:0] w_data,        
    input w_inc, w_clk, w_rst_n,     
    input r_inc, r_clk, r_rst_n        
    );

    wire [ADDRESS_SIZE-1:0] w_addr, r_addr;
    wire [ADDRESS_SIZE:0] w_ptr, r_ptr, w_q2_rptr, r_q2_wptr;

    ff_synchronization #(ADDRESS_SIZE) sync_r2w (    
        .q2(w_q2_rptr), 
        .data_in(r_ptr),
        .clk(w_clk), 
        .rst_n(w_rst_n)
    );

    ff_synchronization #(ADDRESS_SIZE) sync_w2r (       
        .q2(r_q2_wptr), 
        .data_in(w_ptr),
        .clk(r_clk), 
        .rst_n(r_rst_n)
    );

    FIFO_memory #(DATA_SIZE, ADDRESS_SIZE) fifo_mem(    
        .r_data(r_data), 
        .w_data(w_data),
        .w_addr(w_addr), 
        .r_addr(r_addr),
        .w_clk_en(w_inc), 
        .w_full(w_full),
        .w_clk(w_clk)
    );

    rptr_empty #(ADDRESS_SIZE) rptr_empty(         
        .r_empty(r_empty),
        .r_addr(r_addr),
        .r_ptr(r_ptr), 
        .r_q2_wptr(r_q2_wptr),
        .r_inc(r_inc), 
        .r_clk(r_clk),
        .r_rst_n(r_rst_n)
    );

    wptr_full #(ADDRESS_SIZE) wptr_full(          
        .w_full(w_full), 
        .w_addr(w_addr),
        .w_ptr(w_ptr), 
        .w_q2_rptr(w_q2_rptr),
        .w_inc(w_inc), 
        .w_clk(w_clk),
        .w_rst_n(w_rst_n)
    );

endmodule

Asynchronous Fifo/sim/tb_FIFO_Ultimate.v
`timescale 1ns/1ps

module tb_FIFO_Ultimate();

    parameter DATA_SIZE = 16; 
    parameter ADDRESS_SIZE = 8; // Using 4 (16 depth) for faster simulation
    parameter DEPTH = 1 << ADDRESS_SIZE; 

    reg [DATA_SIZE-1:0] w_data;   
    wire [DATA_SIZE-1:0] r_data;  
    wire w_full, r_empty;      
    reg w_inc, r_inc, w_clk, r_clk, w_rst_n, r_rst_n; 

    FIFO #(DATA_SIZE, ADDRESS_SIZE) dut (
        .r_data(r_data), 
        .w_data(w_data),
        .w_full(w_full),
        .r_empty(r_empty),
        .w_inc(w_inc), 
        .r_inc(r_inc), 
        .w_clk(w_clk), 
        .r_clk(r_clk), 
        .w_rst_n(w_rst_n), 
        .r_rst_n(r_rst_n)
    );

    integer i;
    integer seed = 42;

    // 1. Asynchronous Drifting Clocks
    always #5 w_clk = ~w_clk;      // 10ns period (100 MHz)
    always #13.5 r_clk = ~r_clk;   // 27ns period (~37 MHz)
    
    initial begin
        $dumpfile("dump.vcd"); 
        $dumpvars(0, tb_FIFO_Ultimate);
        // Initialize
        w_clk = 0; r_clk = 0;
        w_rst_n = 1; r_rst_n = 1;     
        w_inc = 0; r_inc = 0; w_data = 0;

        // Reset
        $display("[%0t] Resetting FIFO...", $time);
        #40 w_rst_n = 0; r_rst_n = 0;
        #40 w_rst_n = 1; r_rst_n = 1;
        repeat(3) @(negedge w_clk);

        // ---------------------------------------------------------
        // TEST 1: Fill & Overflow Protection (Your DEPTH+3 method)
        // ---------------------------------------------------------
        $display("\n[%0t] --- TEST 1: Fill and Overflow Test ---", $time);
        for (i = 0; i < DEPTH + 3; i = i + 1) begin
            @(negedge w_clk);
            w_data = $random(seed) % 65536;
            w_inc = 1;
            if (w_full) $display("[%0t] Attempting to write %h while FULL (Should be ignored)", $time, w_data);
            else $display("[%0t] Wrote: %h", $time, w_data);
        end
        @(negedge w_clk) w_inc = 0;
        
        // Allow pointers to cross domains
        repeat(10) @(negedge r_clk);

        // ---------------------------------------------------------
        // TEST 2: Empty & Underflow Protection
        // ---------------------------------------------------------
        $display("\n[%0t] --- TEST 2: Empty and Underflow Test ---", $time);
        for (i = 0; i < DEPTH + 3; i = i + 1) begin
            @(negedge r_clk);
            r_inc = 1;
            // Note: r_data updates on posedge, so we wait briefly to display it
            #1; 
            if (r_empty) $display("[%0t] Attempting to read while EMPTY (Data invalid)", $time);
            else $display("[%0t] Read:  %h", $time, r_data);
        end
        @(negedge r_clk) r_inc = 0;

        repeat(10) @(negedge w_clk);

        // ---------------------------------------------------------
        // TEST 3: Simultaneous Read/Write Stress Test
        // ---------------------------------------------------------
        $display("\n[%0t] --- TEST 3: Simultaneous Read/Write ---", $time);
        
        // Start reading and writing continuously
        w_inc = 1;
        r_inc = 1;
        
        // Run for 50 write cycles
        for (i = 0; i < 50; i = i + 1) begin
            @(negedge w_clk);
            if (!w_full) w_data = $random(seed) % 65536;
        end
        
        // Power down stimulus
        @(negedge w_clk) w_inc = 0;
        @(negedge r_clk) r_inc = 0;
        
        #200;
        $display("\n[%0t] --- All Tests Completed ---", $time);
        $finish;
    end

endmodule

Asynchronous Fifo/waveform/dump.vcd
$date
	Sun Aug 09 11:52:52 2026
$end
$version
	Icarus Verilog
$end
$timescale
	1ps
$end
$scope module tb_FIFO_Ultimate $end
$var wire 1 ! w_full $end
$var wire 1 " r_empty $end
$var wire 16 # r_data [15:0] $end
$var reg 1 $ r_clk $end
$var reg 1 % r_inc $end
$var reg 1 & r_rst_n $end
$var reg 1 ' w_clk $end
$var reg 16 ( w_data [15:0] $end
$var reg 1 ) w_inc $end
$var reg 1 * w_rst_n $end
$var integer 32 + i [31:0] $end
$var integer 32 , seed [31:0] $end
$scope module dut $end
$var wire 1 $ r_clk $end
$var wire 1 % r_inc $end
$var wire 1 & r_rst_n $end
$var wire 1 ' w_clk $end
$var wire 16 - w_data [15:0] $end
$var wire 1 ) w_inc $end
$var wire 1 * w_rst_n $end
$var wire 9 . w_q2_rptr [8:0] $end
$var wire 9 / w_ptr [8:0] $end
$var wire 1 ! w_full $end
$var wire 8 0 w_addr [7:0] $end
$var wire 9 1 r_q2_wptr [8:0] $end
$var wire 9 2 r_ptr [8:0] $end
$var wire 1 " r_empty $end
$var wire 16 3 r_data [15:0] $end
$var wire 8 4 r_addr [7:0] $end
$scope module fifo_mem $end
$var wire 16 5 r_data [15:0] $end
$var wire 1 ' w_clk $end
$var wire 1 ) w_clk_en $end
$var wire 16 6 w_data [15:0] $end
$var wire 1 ! w_full $end
$var wire 8 7 w_addr [7:0] $end
$var wire 8 8 r_addr [7:0] $end
$upscope $end
$scope module rptr_empty $end
$var wire 1 $ r_clk $end
$var wire 9 9 r_gray_next [8:0] $end
$var wire 1 % r_inc $end
$var wire 1 & r_rst_n $end
$var wire 9 : r_q2_wptr [8:0] $end
$var wire 1 ; r_empty_val $end
$var wire 9 < r_bin_next [8:0] $end
$var wire 8 = r_addr [7:0] $end
$var reg 9 > r_bin [8:0] $end
$var reg 1 " r_empty $end
$var reg 9 ? r_ptr [8:0] $end
$upscope $end
$scope module sync_r2w $end
$var wire 1 ' clk $end
$var wire 9 @ data_in [8:0] $end
$var wire 1 * rst_n $end
$var reg 9 A q1 [8:0] $end
$var reg 9 B q2 [8:0] $end
$upscope $end
$scope module sync_w2r $end
$var wire 1 $ clk $end
$var wire 1 & rst_n $end
$var wire 9 C data_in [8:0] $end
$var reg 9 D q1 [8:0] $end
$var reg 9 E q2 [8:0] $end
$upscope $end
$scope module wptr_full $end
$var wire 1 ' w_clk $end
$var wire 9 F w_gray_next [8:0] $end
$var wire 1 ) w_inc $end
$var wire 9 G w_q2_rptr [8:0] $end
$var wire 1 * w_rst_n $end
$var wire 1 H w_full_val $end
$var wire 9 I w_bin_next [8:0] $end
$var wire 8 J w_addr [7:0] $end
$var reg 9 K w_bin [8:0] $end
$var reg 1 ! w_full $end
$var reg 9 L w_ptr [8:0] $end
$upscope $end
$upscope $end
$upscope $end
$enddefinitions $end
#0
$dumpvars
bx L
bx K
bx J
bx I
xH
bx G
bx F
bx E
bx D
bx C
bx B
bx A
bx @
bx ?
bx >
bx =
bx <
x;
bx :
bx 9
bx 8
bx 7
b0 6
bx 5
bx 4
bx 3
bx 2
bx 1
bx 0
bx /
bx .
b0 -
b101010 ,
bx +
1*
0)
b0 (
0'
1&
0%
0$
bx #
x"
x!
$end
#5000
1'
#10000
0'
#13500
1$
#15000
1'
#20000
0'
#25000
1'
#27000
0$
#30000
0'
#35000
1'
#40000
1;
0H
b0 4
b0 8
b0 =
b0 9
b0 0
b0 7
b0 J
b0 F
1"
b0 <
b0 >
b0 2
b0 ?
b0 @
b0 1
b0 :
b0 E
b0 D
b0 .
b0 B
b0 G
b0 A
b0 I
b0 K
b0 /
b0 C
b0 L
0!
0'
0&
0*
#40500
1$
#45000
1'
#50000
0'
#54000
0$
#55000
1'
#60000
0'
#65000
1'
#67500
1$
#70000
0'
#75000
1'
#80000
0'
1&
1*
#81000
0$
#85000
1'
#90000
0'
#94500
1$
#95000
1'
#100000
b0 +
0'
#105000
1'
#108000
0$
#110000
b1 F
b1 I
b1 +
1)
b100010000000000 (
b100010000000000 -
b100010000000000 6
b1011000100001110100011 ,
0'
#115000
b1 0
b1 7
b1 J
b11 F
b100010000000000 #
b100010000000000 3
b100010000000000 5
b10 I
b1 K
b1 /
b1 C
b1 L
1'
#120000
b10 +
b111001101001101 (
b111001101001101 -
b111001101001101 6
b10100110100001000111000010001000 ,
0'
#121500
b1 D
1$
#125000
b10 0
b10 7
b10 J
b10 F
b11 I
b10 K
b11 /
b11 C
b11 L
1'
#130000
b11 +
b11100000100 (
b11100000100 -
b11100000100 6
b10000010010011010000010011101001 ,
0'
#135000
b11 0
b11 7
b11 J
b110 F
b100 I
b11 K
b10 /
b10 C
b10 L
1'
0$
#140000
b100 +
b1100010010001011 (
b1100010010001011 -
b1100010010001011 6
b1000101110101011100001110010110 ,
0'
#145000
b100 0
b100 7
b100 J
b111 F
b101 I
b100 K
b110 /
b110 C
b110 L
1'
#148500
0;
b1 1
b1 :
b1 E
b110 D
1$
#150000
b101 +
b11111100010101 (
b11111100010101 -
b11111100010101 6
b10001010101100100011110100011111 ,
0'
#155000
b101 0
b101 7
b101 J
b101 F
b110 I
b101 K
b111 /
b111 C
b111 L
1'
#160000
b110 +
b1000011010110101 (
b1000011010110101 -
b1000011010110101 6
b1011010111101001000010011010100 ,
0'
#162000
0$
#165000
b110 0
b110 7
b110 J
b100 F
b111 I
b110 K
b101 /
b101 C
b101 L
1'
#170000
b111 +
b10001110001010 (
b10001110001010 -
b10001110001010 6
b11000101011000010010000111000101 ,
0'
#175000
b111 0
b111 7
b111 J
b1100 F
b1000 I
b111 K
b100 /
b100 C
b100 L
1'
#175500
0"
b110 1
b110 :
b110 E
b100 D
1$
#180000
b1000 +
b110000111110 (
b110000111110 -
b110000111110 6
b11111010001000000101111000010 ,
0'
#185000
b1000 0
b1000 7
b1000 J
b1101 F
b1001 I
b1000 K
b1100 /
b1100 C
b1100 L
1'
#189000
0$
#190000
b1001 +
b100011100010011 (
b100011100010011 -
b100011100010011 6
b10001001110110000100010001011011 ,
0'
#195000
b1001 0
b1001 7
b1001 J
b1111 F
b1010 I
b1001 K
b1101 /
b1101 C
b1101 L
1'
#200000
b1010 +
b101110101000100 (
b101110101000100 -
b101110101000100 6
b10100010000000100101101111100000 ,
0'
#202500
b100 1
b100 :
b100 E
b1101 D
1$
#205000
b1010 0
b1010 7
b1010 J
b1110 F
b1011 I
b1010 K
b1111 /
b1111 C
b1111 L
1'
#210000
b1011 +
b1111010001101100 (
b1111010001101100 -
b1111010001101100 6
b110110011011011111001001100001 ,
0'
#215000
b1011 0
b1011 7
b1011 J
b1010 F
b1100 I
b1011 K
b1110 /
b1110 C
b1110 L
1'
#216000
0$
#220000
b1100 +
b11000111011 (
b11000111011 -
b11000111011 6
b11101101110110000010010101110 ,
0'
#225000
b1100 0
b1100 7
b1100 J
b1011 F
b1101 I
b1100 K
b1010 /
b1010 C
b1010 L
1'
#229500
b1101 1
b1101 :
b1101 E
b1010 D
1$
#230000
b1101 +
b1001011010100101 (
b1001011010100101 -
b1001011010100101 6
b1010010101011011001010101010111 ,
0'
#235000
b1101 0
b1101 7
b1101 J
b1001 F
b1110 I
b1101 K
b1011 /
b1011 C
b1011 L
1'
#240000
b1110 +
b1100110101 (
b1100110101 -
b1100110101 6
b10011010111011010000000110101100 ,
0'
#243000
0$
#245000
b1110 0
b1110 7
b1110 J
b1000 F
b1111 I
b1110 K
b1001 /
b1001 C
b1001 L
1'
#250000
b1111 +
b1010000110101 (
b1010000110101 -
b1010000110101 6
b11010100011000001001010111101 ,
0'
#255000
b1111 0
b1111 7
b1111 J
b11000 F
b10000 I
b1111 K
b1000 /
b1000 C
b1000 L
1'
#256500
b1010 1
b1010 :
b1010 E
b1000 D
1$
#260000
b10000 +
b1001110011100011 (
b1001110011100011 -
b1001110011100011 6
b1110001110110111001101001011010 ,
0'
#265000
b10000 0
b10000 7
b10000 J
b11001 F
b10001 I
b10000 K
b11000 /
b11000 C
b11000 L
1'
#270000
b10001 +
b10111111011100 (
b10111111011100 -
b10111111011100 6
b11101110000010110010110000010011 ,
0'
0$
#275000
b10001 0
b10001 7
b10001 J
b11011 F
b10010 I
b10001 K
b11001 /
b11001 C
b11001 L
1'
#280000
b10010 +
b100010010111000 (
b100010010111000 -
b100010010111000 6
b1011100010000100100001000111000 ,
0'
#283500
b1000 1
b1000 :
b1000 E
b11001 D
1$
#285000
b10010 0
b10010 7
b10010 J
b11010 F
b10011 I
b10010 K
b11011 /
b11011 C
b11011 L
1'
#290000
b10011 +
b1110000100000001 (
b1110000100000001 -
b1110000100000001 6
b10000000101000111101111011011001 ,
0'
#295000
b10011 0
b10011 7
b10011 J
b11110 F
b10100 I
b10011 K
b11010 /
b11010 C
b11010 L
1'
#297000
0$
#300000
b10100 +
b111101001101000 (
b111101001101000 -
b111101001101000 6
b110100011000110111100011000110 ,
0'
#305000
b10100 0
b10100 7
b10100 J
b11111 F
b10101 I
b10100 K
b11110 /
b11110 C
b11110 L
1'
#310000
b10101 +
b1100011011110011 (
b1100011011110011 -
b1100011011110011 6
b1111001100011111100010010001111 ,
0'
#310500
b11001 1
b11001 :
b11001 E
b11110 D
1$
#315000
b10101 0
b10101 7
b10101 J
b11101 F
b10110 I
b10101 K
b11111 /
b11111 C
b11111 L
1'
#320000
b10110 +
b1010101011010011 (
b1010101011010011 -
b1010101011010011 6
b1101001101010101010100110000100 ,
0'
#324000
0$
#325000
b10110 0
b10110 7
b10110 J
b11100 F
b10111 I
b10110 K
b11101 /
b11101 C
b11101 L
1'
#330000
b10111 +
b111010111100011 (
b111010111100011 -
b111010111100011 6
b11110001110010010111001010110101 ,
0'
#335000
b10111 0
b10111 7
b10111 J
b10100 F
b11000 I
b10111 K
b11100 /
b11100 C
b11100 L
1'
#337500
b11110 1
b11110 :
b11110 E
b11100 D
1$
#340000
b11000 +
b110010010111 (
b110010010111 -
b110010010111 6
b1001011110110010000101111110010 ,
0'
#345000
b11000 0
b11000 7
b11000 J
b10101 F
b11001 I
b11000 K
b10100 /
b10100 C
b10100 L
1'
#350000
b11001 +
b1101110110011100 (
b1101110110011100 -
b1101110110011100 6
b11001110010110111101101011001011 ,
0'
#351000
0$
#355000
b11001 0
b11001 7
b11001 J
b10111 F
b11010 I
b11001 K
b10101 /
b10101 C
b10101 L
1'
#360000
b11010 +
b1000010110001000 (
b1000010110001000 -
b1000010110001000 6
b11000100011101011000001110010000 ,
0'
#364500
b11100 1
b11100 :
b11100 E
b10101 D
1$
#365000
b11010 0
b11010 7
b11010 J
b10110 F
b11011 I
b11010 K
b10111 /
b10111 C
b10111 L
1'
#370000
b11011 +
b1010110110011010 (
b1010110110011010 -
b1010110110011010 6
b11001101010110001010101001010001 ,
0'
#375000
b11011 0
b11011 7
b11011 J
b10010 F
b11100 I
b11011 K
b10110 /
b10110 C
b10110 L
1'
#378000
0$
#380000
b11100 +
b1000000100110101 (
b1000000100110101 -
b1000000100110101 6
b10011010111101110111111111011110 ,
0'
#385000
b11100 0
b11100 7
b11100 J
b10011 F
b11101 I
b11100 K
b10010 /
b10010 C
b10010 L
1'
#390000
b11101 +
b1010110001010011 (
b1010110001010011 -
b1010110001010011 6
b101001100011011010101011000111 ,
0'
#391500
b10101 1
b10101 :
b10101 E
b10010 D
1$
#395000
b11101 0
b11101 7
b11101 J
b10001 F
b11110 I
b11101 K
b10011 /
b10011 C
b10011 L
1'
#400000
b11110 +
b1101111001000101 (
b1101111001000101 -
b1101111001000101 6
b100010111001001101110001011100 ,
0'
#405000
b11110 0
b11110 7
b11110 J
b10000 F
b11111 I
b11110 K
b10001 /
b10001 C
b10001 L
1'
0$
#410000
b11111 +
b10001011011001 (
b10001011011001 -
b10001011011001 6
b1101100110100010010000110101101 ,
0'
#415000
b11111 0
b11111 7
b11111 J
b110000 F
b100000 I
b11111 K
b10000 /
b10000 C
b10000 L
1'
#418500
b10010 1
b10010 :
b10010 E
b10000 D
1$
#420000
b100000 +
b1100001111000111 (
b1100001111000111 -
b1100001111000111 6
b11100011110110101100000010001010 ,
0'
#425000
b100000 0
b100000 7
b100000 J
b110001 F
b100001 I
b100000 K
b110000 /
b110000 C
b110000 L
1'
#430000
b100001 +
b11001010100100 (
b11001010100100 -
b11001010100100 6
b1010010011111010011000010000011 ,
0'
#432000
0$
#435000
b100001 0
b100001 7
b100001 J
b110011 F
b100010 I
b100001 K
b110001 /
b110001 C
b110001 L
1'
#440000
b100010 +
b1000000100110100 (
b1000000100110100 -
b1000000100110100 6
b10011010001110010111111111101000 ,
0'
#445000
b100010 0
b100010 7
b100010 J
b110010 F
b100011 I
b100010 K
b110011 /
b110011 C
b110011 L
1'
#445500
b10000 1
b10000 :
b10000 E
b110011 D
1$
#450000
b100011 +
b11011111010110 (
b11011111010110 -
b11011111010110 6
b11101011011100100011010011001001 ,
0'
#455000
b100011 0
b100011 7
b100011 J
b110110 F
b100100 I
b100011 K
b110010 /
b110010 C
b110010 L
1'
#459000
0$
#460000
b100100 +
b111101100010111 (
b111101100010111 -
b111101100010111 6
b10001011111010110111100111110110 ,
0'
#465000
b100100 0
b100100 7
b100100 J
b110111 F
b100101 I
b100100 K
b110110 /
b110110 C
b110110 L
1'
#470000
b100101 +
b10100011110101 (
b10100011110101 -
b10100011110101 6
b1111010101110000010011111111111 ,
0'
#472500
b110011 1
b110011 :
b110011 E
b110110 D
1$
#475000
b100101 0
b100101 7
b100101 J
b110101 F
b100110 I
b100101 K
b110111 /
b110111 C
b110111 L
1'
#480000
b100110 +
b1111110110001110 (
b1111110110001110 -
b1111110110001110 6
b11000111011111101111101000110100 ,
0'
#485000
b100110 0
b100110 7
b100110 J
b110100 F
b100111 I
b100110 K
b110101 /
b110101 C
b110101 L
1'
#486000
0$
#490000
b100111 +
b1011011 (
b1011011 -
b1011011 6
b101101100101101111111110100101 ,
0'
#495000
b100111 0
b100111 7
b100111 J
b111100 F
b101000 I
b100111 K
b110100 /
b110100 C
b110100 L
1'
#499500
b110110 1
b110110 :
b110110 E
b110100 D
1$
#500000
b101000 +
b1101001011001 (
b1101001011001 -
b1101001011001 6
b101100100010110001100000100010 ,
0'
#505000
b101000 0
b101000 7
b101000 J
b111101 F
b101001 I
b101000 K
b111100 /
b111100 C
b111100 L
1'
#510000
b101001 +
b111110100111 (
b111110100111 -
b111110100111 6
b11010011101111100000110100111011 ,
0'
#513000
0$
#515000
b101001 0
b101001 7
b101001 J
b111111 F
b101010 I
b101001 K
b111101 /
b111101 C
b111101 L
1'
#520000
b101010 +
b1001100010000110 (
b1001100010000110 -
b1001100010000110 6
b1000011000101111001011101000000 ,
0'
#525000
b101010 0
b101010 7
b101010 J
b111110 F
b101011 I
b101010 K
b111111 /
b111111 C
b111111 L
1'
#526500
b110100 1
b110100 :
b110100 E
b111111 D
1$
#530000
b101011 +
b110000100000111 (
b110000100000111 -
b110000100000111 6
b10000011110100100101111001000001 ,
0'
#535000
b101011 0
b101011 7
b101011 J
b111010 F
b101100 I
b101011 K
b111110 /
b111110 C
b111110 L
1'
#540000
b101100 +
b1100100100111000 (
b1100100100111000 -
b1100100100111000 6
b10011100011111111100011100001110 ,
0'
0$
#545000
b101100 0
b101100 7
b101100 J
b111011 F
b101101 I
b101100 K
b111010 /
b111010 C
b111010 L
1'
#550000
b101101 +
b1111100101100 (
b1111100101100 -
b1111100101100 6
b10010110011111000001110000110111 ,
0'
#553500
b111111 1
b111111 :
b111111 E
b111010 D
1$
#555000
b101101 0
b101101 7
b101101 J
b111001 F
b101110 I
b101101 K
b111011 /
b111011 C
b111011 L
1'
#560000
b101110 +
b110010111010110 (
b110010111010110 -
b110010111010110 6
b11101011000010000110001100001100 ,
0'
#565000
b101110 0
b101110 7
b101110 J
b111000 F
b101111 I
b101110 K
b111001 /
b111001 C
b111001 L
1'
#567000
0$
#570000
b101111 +
b1110111000001011 (
b1110111000001011 -
b1110111000001011 6
b101110010101110110010011101 ,
0'
#575000
b101111 0
b101111 7
b101111 J
b101000 F
b110000 I
b101111 K
b111000 /
b111000 C
b111000 L
1'
#580000
b110000 +
b111010110111100 (
b111010110111100 -
b111010110111100 6
b11011110001000000111001010111010 ,
0'
#580500
b111010 1
b111010 :
b111010 E
b111000 D
1$
#585000
b110000 0
b110000 7
b110000 J
b101001 F
b110001 I
b110000 K
b101000 /
b101000 C
b101000 L
1'
#590000
b110001 +
b101001111110001 (
b101001111110001 -
b101001111110001 6
b11111000100010010101000011110011 ,
0'
#594000
0$
#595000
b110001 0
b110001 7
b110001 J
b101011 F
b110010 I
b110001 K
b101001 /
b101001 C
b101001 L
1'
#600000
b110010 +
b10101010100000 (
b10101010100000 -
b10101010100000 6
b1010000000001010010100110011000 ,
0'
#605000
b110010 0
b110010 7
b110010 J
b101010 F
b110011 I
b110010 K
b101011 /
b101011 C
b101011 L
1'
#607500
b111000 1
b111000 :
b111000 E
b101011 D
1$
#610000
b110011 +
b100100000001 (
b100100000001 -
b100100000001 6
b10000000110101110000011010111001 ,
0'
#615000
b110011 0
b110011 7
b110011 J
b101110 F
b110100 I
b110011 K
b101010 /
b101010 C
b101010 L
1'
#620000
b110100 +
b1100100000111100 (
b1100100000111100 -
b1100100000111100 6
b11110010000001100011100100110 ,
0'
#621000
0$
#625000
b110100 0
b110100 7
b110100 J
b101111 F
b110101 I
b110100 K
b101110 /
b101110 C
b101110 L
1'
#630000
b110101 +
b110100010010110 (
b110100010010110 -
b110100010010110 6
b1001011001000100110011101101111 ,
0'
#634500
b101011 1
b101011 :
b101011 E
b101110 D
1$
#635000
b110101 0
b110101 7
b110101 J
b101101 F
b110110 I
b110101 K
b101111 /
b101111 C
b101111 L
1'
#640000
b110110 +
b111100010100010 (
b111100010100010 -
b111100010100010 6
b1010001001111000111011011100100 ,
0'
#645000
b110110 0
b110110 7
b110110 J
b101100 F
b110111 I
b110110 K
b101101 /
b101101 C
b101101 L
1'
#648000
0$
#650000
b110111 +
b1100101100101100 (
b1100101100101100 -
b1100101100101100 6
b10010110010110001100100010010101 ,
0'
#655000
b110111 0
b110111 7
b110111 J
b100100 F
b111000 I
b110111 K
b101100 /
b101100 C
b101100 L
1'
#660000
b111000 +
b11001101011111 (
b11001101011111 -
b11001101011111 6
b10101111110111010011000001010010 ,
0'
#661500
b101110 1
b101110 :
b101110 E
b101100 D
1$
#665000
b111000 0
b111000 7
b111000 J
b100101 F
b111001 I
b111000 K
b100100 /
b100100 C
b100100 L
1'
#670000
b111001 +
b1101110001111111 (
b1101110001111111 -
b1101110001111111 6
b111111111001011101101110101011 ,
0'
#675000
b111001 0
b111001 7
b111001 J
b100111 F
b111010 I
b111001 K
b100101 /
b100101 C
b100101 L
1'
0$
#680000
b111010 +
b1001100101100101 (
b1001100101100101 -
b1001100101100101 6
b10110010111000111001011011110000 ,
0'
#685000
b111010 0
b111010 7
b111010 J
b100110 F
b111011 I
b111010 K
b100111 /
b100111 C
b100111 L
1'
#688500
b101100 1
b101100 :
b101100 E
b100111 D
1$
#690000
b111011 +
b1000011001011 (
b1000011001011 -
b1000011001011 6
b1100101110110100000111000110001 ,
0'
#695000
b111011 0
b111011 7
b111011 J
b100010 F
b111100 I
b111011 K
b100110 /
b100110 C
b100110 L
1'
#700000
b111100 +
b1101110101100001 (
b1101110101100001 -
b1101110101100001 6
b10110000100001101101101000111110 ,
0'
#702000
0$
#705000
b111100 0
b111100 7
b111100 J
b100011 F
b111101 I
b111100 K
b100010 /
b100010 C
b100010 L
1'
#710000
b111101 +
b1110101000011110 (
b1110101000011110 -
b1110101000011110 6
b1111010011111110100110100111 ,
0'
#715000
b111101 0
b111101 7
b111101 J
b100001 F
b111110 I
b111101 K
b100011 /
b100011 C
b100011 L
1'
#715500
b100111 1
b100111 :
b100111 E
b100011 D
1$
#720000
b111110 +
b1001011001110111 (
b1001011001110111 -
b1001011001110111 6
b111011100000101001010110111100 ,
0'
#725000
b111110 0
b111110 7
b111110 J
b100000 F
b111111 I
b111110 K
b100001 /
b100001 C
b100001 L
1'
#729000
0$
#730000
b111111 +
b111010110111101 (
b111010110111101 -
b111010110111101 6
b11011110111010000111001110001101 ,
0'
#735000
b111111 0
b111111 7
b111111 J
b1100000 F
b1000000 I
b111111 K
b100000 /
b100000 C
b100000 L
1'
#740000
b1000000 +
b1011001110000011 (
b1011001110000011 -
b1011001110000011 6
b11000001100011111011000011101010 ,
0'
#742500
b100011 1
b100011 :
b100011 E
b100000 D
1$
#745000
b1000000 0
b1000000 7
b1000000 J
b1100001 F
b1000001 I
b1000000 K
b1100000 /
b1100000 C
b1100000 L
1'
#750000
b1000001 +
b1000111111111001 (
b1000111111111001 -
b1000111111111001 6
b11111100111101101000110101100011 ,
0'
#755000
b1000001 0
b1000001 7
b1000001 J
b1100011 F
b1000010 I
b1000001 K
b1100001 /
b1100001 C
b1100001 L
1'
#756000
0$
#760000
b1000010 +
b100000101001000 (
b100000101001000 -
b100000101001000 6
b10100100000000000011111101001000 ,
0'
#765000
b1000010 0
b1000010 7
b1000010 J
b1100010 F
b1000011 I
b1000010 K
b1100011 /
b1100011 C
b1100011 L
1'
#769500
b100000 1
b100000 :
b100000 E
b1100011 D
1$
